[{"items":[{"id":"m2","name":"Margherita Pizza","price":"12.99","description":"A classic pizza with fresh mozzarella, tomatoes, and basil on a thin and crispy crust.","image":"images/margherita-pizza.jpg","quantity":1},{"id":"m1","name":"Mac & Cheese","price":"8.99","description":"Creamy cheddar cheese mixed with perfectly cooked macaroni, topped with crispy breadcrumbs. A classic comfort food.","image":"images/mac-and-cheese.jpg","quantity":1}],"customer":{"name":"Robert Lewandows","email":"rlewy@gmail.com","street":"123 Camp Nou","postal-code":"98876","city":"Barcelona"},"id":"368.3778305910283"},{"items":[{"id":"m2","name":"Margherita Pizza","price":"12.99","description":"A classic pizza with fresh mozzarella, tomatoes, and basil on a thin and crispy crust.","image":"images/margherita-pizza.jpg","quantity":1},{"id":"m1","name":"Mac & Cheese","price":"8.99","description":"Creamy cheddar cheese mixed with perfectly cooked macaroni, topped with crispy breadcrumbs. A classic comfort food.","image":"images/mac-and-cheese.jpg","quantity":1}],"customer":{"name":"Robert Lewandows","email":"rlewy@gmail.com","street":"123 Camp Nou","postal-code":"98876","city":"Barcelona"},"id":"353.764792289075"},{"items":[{"id":"m2","name":"Margherita Pizza","price":"12.99","description":"A classic pizza with fresh mozzarella, tomatoes, and basil on a thin and crispy crust.","image":"images/margherita-pizza.jpg","quantity":1},{"id":"m1","name":"Mac & Cheese","price":"8.99","description":"Creamy cheddar cheese mixed with perfectly cooked macaroni, topped with crispy breadcrumbs. A classic comfort food.","image":"images/mac-and-cheese.jpg","quantity":1}],"customer":{"name":"Robert Lewandows","email":"rlewy@gmail.com","street":"123 Camp Nou","postal-code":"98876","city":"Barcelona"},"id":"579.7595459540288"},{"items":[{"id":"m2","name":"Margherita Pizza","price":"12.99","description":"A classic pizza with fresh mozzarella, tomatoes, and basil on a thin and crispy crust.","image":"images/margherita-pizza.jpg","quantity":1}],"customer":{"name":"Robert Lewandows","email":"rlewy@gmail.com","street":"123 Camp Nou","postal-code":"98876","city":"Barcelona"},"id":"323.2194912956108"},{"items":[{"id":"m2","name":"Margherita Pizza","price":"12.99","description":"A classic pizza with fresh mozzarella, tomatoes, and basil on a thin and crispy crust.","image":"images/margherita-pizza.jpg","quantity":1}],"customer":{"name":"Robert Lewandows","email":"rlewy@gmail.com","street":"123 Camp Nou","postal-code":"98876","city":"Barcelona"},"id":"542.9813032190933"},{"items":[{"id":"m2","name":"Margherita Pizza","price":"12.99","description":"A classic pizza with fresh mozzarella, tomatoes, and basil on a thin and crispy crust.","image":"images/margherita-pizza.jpg","quantity":1}],"customer":{"name":"Robert Lewandows","email":"rlewy@gmail.com","street":"123 Camp Nou","postal-code":"98876","city":"Barcelona"},"id":"955.538889917186"},{"items":[{"id":"m2","name":"Margherita Pizza","price":"12.99","description":"A classic pizza with fresh mozzarella, tomatoes, and basil on a thin and crispy crust.","image":"images/margherita-pizza.jpg","quantity":1},{"id":"m1","name":"Mac & Cheese","price":"8.99","description":"Creamy cheddar cheese mixed with perfectly cooked macaroni, topped with crispy breadcrumbs. A classic comfort food.","image":"images/mac-and-cheese.jpg","quantity":1}],"customer":{"name":"Robert Lewandows","email":"rlewy@gmail.com","street":"123 Camp Nou","postal-code":"98876","city":"Barcelona"},"id":"305.40637365728406"},{"items":[{"id":"m2","name":"Margherita Pizza","price":"12.99","description":"A classic pizza with fresh mozzarella, tomatoes, and basil on a thin and crispy crust.","image":"images/margherita-pizza.jpg","quantity":1},{"id":"m1","name":"Mac & Cheese","price":"8.99","description":"Creamy cheddar cheese mixed with perfectly cooked macaroni, topped with crispy breadcrumbs. A classic comfort food.","image":"images/mac-and-cheese.jpg","quantity":1}],"customer":{"name":"Robert Lewandows","email":"rlewy@gmail.com","street":"123 Camp Nou","postal-code":"98876","city":"Barcelona"},"id":"446.0910807760861"},{"items":[{"id":"m6","name":"Grilled Chicken Sandwich","price":"10.99","description":"Tender grilled chicken breast with avocado, bacon, lettuce, and honey mustard on a toasted bun.","image":"images/grilled-chicken-sandwich.jpg","quantity":1},{"id":"m5","name":"Veggie Burger","price":"9.99","description":"A juicy veggie patty served on a whole grain bun with lettuce, tomato, and a tangy sauce.","image":"images/veggie-burger.jpg","quantity":1}],"customer":{"name":"Robert Lewandows","email":"rlewy@gmail.com","street":"123 Camp Nou","postal-code":"98876","city":"Barcelona"},"id":"640.8771279589666"},{"items":[{"id":"m2","name":"Margherita Pizza","price":"12.99","description":"A classic pizza with fresh mozzarella, tomatoes, and basil on a thin and crispy crust.","image":"images/margherita-pizza.jpg","quantity":1},{"id":"m1","name":"Mac & Cheese","price":"8.99","description":"Creamy cheddar cheese mixed with perfectly cooked macaroni, topped with crispy breadcrumbs. A classic comfort food.","image":"images/mac-and-cheese.jpg","quantity":1}],"customer":{"name":"Robert Lewandows","email":"rlewy@gmail.com","street":"123 Camp Nou","postal-code":"98876","city":"Barcelona"},"id":"470.9325350677338"},{"items":[{"id":"m2","name":"Margherita Pizza","price":"12.99","description":"A classic pizza with fresh mozzarella, tomatoes, and basil on a thin and crispy crust.","image":"images/margherita-pizza.jpg","quantity":1},{"id":"m1","name":"Mac & Cheese","price":"8.99","description":"Creamy cheddar cheese mixed with perfectly cooked macaroni, topped with crispy breadcrumbs. A classic comfort food.","image":"images/mac-and-cheese.jpg","quantity":1}],"customer":{"name":"Robert Lewandows","email":"rlewy@gmail.com","street":"123 Camp Nou","postal-code":"98876","city":"Barcelona"},"id":"145.3807324438363"},{"items":[{"id":"m2","name":"Margherita Pizza","price":"12.99","description":"A classic pizza with fresh mozzarella, tomatoes, and basil on a thin and crispy crust.","image":"images/margherita-pizza.jpg","quantity":1},{"id":"m1","name":"Mac & Cheese","price":"8.99","description":"Creamy cheddar cheese mixed with perfectly cooked macaroni, topped with crispy breadcrumbs. A classic comfort food.","image":"images/mac-and-cheese.jpg","quantity":1}],"customer":{"name":"asd","email":"rlewy@gmail.com","street":"asd","postal-code":"asd","city":"asd"},"id":"33.07769695137242"},{"items":[{"id":"m2","name":"Margherita Pizza","price":"12.99","description":"A classic pizza with fresh mozzarella, tomatoes, and basil on a thin and crispy crust.","image":"images/margherita-pizza.jpg","quantity":1},{"id":"m1","name":"Mac & Cheese","price":"8.99","description":"Creamy cheddar cheese mixed with perfectly cooked macaroni, topped with crispy breadcrumbs. A classic comfort food.","image":"images/mac-and-cheese.jpg","quantity":1}],"customer":{"name":"asd","email":"rlewy@gmail.com","street":"asd","postal-code":"asd","city":"asd"},"id":"712.6443023114291"},{"items":[{"id":"m2","name":"Margherita Pizza","price":"12.99","description":"A classic pizza with fresh mozzarella, tomatoes, and basil on a thin and crispy crust.","image":"images/margherita-pizza.jpg","quantity":1},{"id":"m1","name":"Mac & Cheese","price":"8.99","description":"Creamy cheddar cheese mixed with perfectly cooked macaroni, topped with crispy breadcrumbs. A classic comfort food.","image":"images/mac-and-cheese.jpg","quantity":1}],"customer":{"name":"asd","email":"rlewy@gmail.com","street":"asd","postal-code":"asd","city":"asd"},"id":"737.088443088566"},{"items":[{"id":"m1","name":"Mac & Cheese","price":"8.99","description":"Creamy cheddar cheese mixed with perfectly cooked macaroni, topped with crispy breadcrumbs. A classic comfort food.","image":"images/mac-and-cheese.jpg","quantity":1}],"customer":{"name":"Aaradhya Poudyal","email":"rlewy@gmail.com","street":"123 Camp Nou","postal-code":"98876","city":"Barcelona"},"id":"301.9591903197967"},{"items":[{"id":"m1","name":"Mac & Cheese","price":"8.99","description":"Creamy cheddar cheese mixed with perfectly cooked macaroni, topped with crispy breadcrumbs. A classic comfort food.","image":"images/mac-and-cheese.jpg","quantity":1}],"customer":{"name":"Aaradhya Poudyal","email":"rlewy@gmail.com","street":"123 Camp Nou","postal-code":"98876","city":"Barcelona"},"id":"646.8171274342523"},{"items":[{"id":"m1","name":"Mac & Cheese","price":"8.99","description":"Creamy cheddar cheese mixed with perfectly cooked macaroni, topped with crispy breadcrumbs. A classic comfort food.","image":"images/mac-and-cheese.jpg","quantity":1}],"customer":{"name":"Aaradhya Poudyal","email":"rlewy@gmail.com","street":"123 Camp Nou","postal-code":"98876","city":"Barcelona"},"id":"349.411093476256"},{"items":[{"id":"m2","name":"Margherita Pizza","price":"12.99","description":"A classic pizza with fresh mozzarella, tomatoes, and basil on a thin and crispy crust.","image":"images/margherita-pizza.jpg","quantity":1},{"id":"m1","name":"Mac & Cheese","price":"8.99","description":"Creamy cheddar cheese mixed with perfectly cooked macaroni, topped with crispy breadcrumbs. A classic comfort food.","image":"images/mac-and-cheese.jpg","quantity":1}],"customer":{"name":"Aaradhya Poudyal","email":"rlewy@gmail.com","street":"123 Camp Nou","postal-code":"98876","city":"Barcelona"},"id":"41.918034835491724"},{"items":[{"id":"m2","name":"Margherita Pizza","price":"12.99","description":"A classic pizza with fresh mozzarella, tomatoes, and basil on a thin and crispy crust.","image":"images/margherita-pizza.jpg","quantity":1},{"id":"m1","name":"Mac & Cheese","price":"8.99","description":"Creamy cheddar cheese mixed with perfectly cooked macaroni, topped with crispy breadcrumbs. A classic comfort food.","image":"images/mac-and-cheese.jpg","quantity":1}],"customer":{"name":"Robert Lewandows","email":"rlewy@gmail.com","street":"123 Camp Nou","postal-code":"98876","city":"Barcelona"},"id":"314.7801176481082"},{"items":[{"id":"m2","name":"Margherita Pizza","price":"12.99","description":"A classic pizza with fresh mozzarella, tomatoes, and basil on a thin and crispy crust.","image":"images/margherita-pizza.jpg","quantity":1},{"id":"m1","name":"Mac & Cheese","price":"8.99","description":"Creamy cheddar cheese mixed with perfectly cooked macaroni, topped with crispy breadcrumbs. A classic comfort food.","image":"images/mac-and-cheese.jpg","quantity":1}],"customer":{"name":"Robert Lewandows","email":"rlewy@gmail.com","street":"123 Camp Nou","postal-code":"98876","city":"Barcelona"},"id":"479.30909721322234"},{"items":[{"id":"m2","name":"Margherita Pizza","price":"12.99","description":"A classic pizza with fresh mozzarella, tomatoes, and basil on a thin and crispy crust.","image":"images/margherita-pizza.jpg","quantity":1},{"id":"m1","name":"Mac & Cheese","price":"8.99","description":"Creamy cheddar cheese mixed with perfectly cooked macaroni, topped with crispy breadcrumbs. A classic comfort food.","image":"images/mac-and-cheese.jpg","quantity":1}],"customer":{"name":"Robert Lewandows","email":"johncena@gmail.com","street":"123 Camp Nou","postal-code":"98876","city":"Barcelona"},"id":"354.59023011042956"},{"items":[{"id":"m2","name":"Margherita Pizza","price":"12.99","description":"A classic pizza with fresh mozzarella, tomatoes, and basil on a thin and crispy crust.","image":"images/margherita-pizza.jpg","quantity":1},{"id":"m1","name":"Mac & Cheese","price":"8.99","description":"Creamy cheddar cheese mixed with perfectly cooked macaroni, topped with crispy breadcrumbs. A classic comfort food.","image":"images/mac-and-cheese.jpg","quantity":1}],"customer":{"name":"Robert Lewandows","email":"johncena@gmail.com","street":"123 Camp Nou","postal-code":"98876","city":"Barcelona"},"id":"778.4751538280918"},{"items":[{"id":"m1","name":"Mac & Cheese","price":"8.99","description":"Creamy cheddar cheese mixed with perfectly cooked macaroni, topped with crispy breadcrumbs. A classic comfort food.","image":"images/mac-and-cheese.jpg","quantity":1},{"id":"m2","name":"Margherita Pizza","price":"12.99","description":"A classic pizza with fresh mozzarella, tomatoes, and basil on a thin and crispy crust.","image":"images/margherita-pizza.jpg","quantity":1}],"customer":{"name":"Robert Lewandows","email":"johncena@gmail.com","street":"123 Camp Nou","postal-code":"98876","city":"Barcelona"},"id":"397.5548700058198"},{"items":[{"id":"m1","name":"Mac & Cheese","price":"8.99","description":"Creamy cheddar cheese mixed with perfectly cooked macaroni, topped with crispy breadcrumbs. A classic comfort food.","image":"images/mac-and-cheese.jpg","quantity":1},{"id":"m2","name":"Margherita Pizza","price":"12.99","description":"A classic pizza with fresh mozzarella, tomatoes, and basil on a thin and crispy crust.","image":"images/margherita-pizza.jpg","quantity":1}],"customer":{"name":"Robert Lewandows","email":"rlewy@gmail.com","street":"123 Camp Nou","postal-code":"98876","city":"Barcelona"},"id":"321.10822439431087"},{"items":[{"id":"m1","name":"Mac & Cheese","price":"8.99","description":"Creamy cheddar cheese mixed with perfectly cooked macaroni, topped with crispy breadcrumbs. A classic comfort food.","image":"images/mac-and-cheese.jpg","quantity":1},{"id":"m2","name":"Margherita Pizza","price":"12.99","description":"A classic pizza with fresh mozzarella, tomatoes, and basil on a thin and crispy crust.","image":"images/margherita-pizza.jpg","quantity":1},{"id":"m3","name":"Caesar Salad","price":"7.99","description":"Romaine lettuce tossed in Caesar dressing, topped with croutons and parmesan shavings.","image":"images/caesar-salad.jpg","quantity":2}],"customer":{"name":"Robert Lewandows","email":"rlewy@gmail.com","street":"asd","postal-code":"98876","city":"Barcelona"},"id":"220.54354500813278"},{"items":[{"id":"m1","name":"Mac & Cheese","price":"8.99","description":"Creamy cheddar cheese mixed with perfectly cooked macaroni, topped with crispy breadcrumbs. A classic comfort food.","image":"images/mac-and-cheese.jpg","quantity":1},{"id":"m2","name":"Margherita Pizza","price":"12.99","description":"A classic pizza with fresh mozzarella, tomatoes, and basil on a thin and crispy crust.","image":"images/margherita-pizza.jpg","quantity":1},{"id":"m3","name":"Caesar Salad","price":"7.99","description":"Romaine lettuce tossed in Caesar dressing, topped with croutons and parmesan shavings.","image":"images/caesar-salad.jpg","quantity":2}],"customer":{"name":"Robert Lewandows","email":"rlewy@gmail.com","street":"asd","postal-code":"98876","city":"Barcelona"},"id":"890.0906488368214"},{"items":[{"id":"m3","name":"Caesar Salad","price":"7.99","description":"Romaine lettuce tossed in Caesar dressing, topped with croutons and parmesan shavings.","image":"images/caesar-salad.jpg","quantity":4}],"customer":{"name":"Robert Lewandows","email":"rlewy@gmail.com","street":"123 Camp Nou","postal-code":"98876","city":"Berkeley "},"id":"677.5016643584908"},{"items":[{"id":"m2","name":"Margherita Pizza","price":"12.99","description":"A classic pizza with fresh mozzarella, tomatoes, and basil on a thin and crispy crust.","image":"images/margherita-pizza.jpg","quantity":1}],"customer":{"name":"Robert Lewandows","email":"rlewy@gmail.com","street":"123 Camp Nou","postal-code":"98876","city":"Barcelona"},"id":"336.1335193692738"}]